<?xml version="1.0" encoding="UTF-8"?>

<ValueSet xmlns="http://hl7.org/fhir">
  <id value="KBV-VS-WEST-Diagnoseart"/>
  <text>
    <status value="generated"/><div xmlns="http://www.w3.org/1999/xhtml"><p class="res-header-id"><b>Generated Narrative: ValueSet KBV-VS-WEST-Diagnoseart</b></p><a name="KBV-VS-WEST-Diagnoseart"> </a><a name="hcKBV-VS-WEST-Diagnoseart"> </a><ul><li>Include all codes defined in <a href="CodeSystem-KBV-CS-WEST-Diagnoseart.html"><code>https://fhir.kbv.de/CodeSystem/KBV_CS_WEST_Diagnoseart</code></a><span title="Version is not explicitly stated, which means it is fixed to the version provided in this specification"> version &#x1F4E6;1.0.0-kommentierung</span></li></ul></div>
  </text>
  <url value="https://fhir.kbv.de/ValueSet/KBV_VS_WEST_Diagnoseart"/>
  <version value="1.0.0-kommentierung"/>
  <name value="KBV_VS_WEST_Diagnoseart"/>
  <title value="KBV_VS_WEST_Diagnoseart"/>
  <status value="draft"/>
  <experimental value="false"/>
  <date value="2026-03-18T12:55:48+01:00"/>
  <publisher value="mio42 GmbH"/>
  <contact>
    <name value="mio42 GmbH"/>
    <telecom>
      <system value="url"/>
      <value value="https://mio.kbv.de"/>
    </telecom>
    <telecom>
      <system value="email"/>
      <value value="hello@mio42.de"/>
    </telecom>
  </contact>
  <description value="Diagnosearten"/>
  <jurisdiction>
    <coding>
      <system value="urn:iso:std:iso:3166"/>
      <code value="DE"/>
      <display value="Germany"/>
    </coding>
  </jurisdiction>
  <copyright value="Kassenaerztliche Bundesvereinigung"/>
  <compose>
    <include>
      <system value="https://fhir.kbv.de/CodeSystem/KBV_CS_WEST_Diagnoseart"/>
    </include>
  </compose>
</ValueSet>